MANIFEST.in
README.md
setup.py
suds_passworddigest/__init__.py
suds_passworddigest/tests.py
suds_passworddigest/token.py
suds_passworddigest.egg-info/PKG-INFO
suds_passworddigest.egg-info/SOURCES.txt
suds_passworddigest.egg-info/dependency_links.txt
suds_passworddigest.egg-info/not-zip-safe
suds_passworddigest.egg-info/requires.txt
suds_passworddigest.egg-info/top_level.txt