Metadata-Version: 1.0
Name: suds-passworddigest
Version: 0.1.1
Summary: adds Web Services Security PasswordDigest authentication to SUDS
Home-page: http://github.com/suvit/suds-passworddigest
Author: Victor Safronovich
Author-email: vsafronovich@gmail.com
License: MIT
Platform: UNKNOWN
